bax/__init__.py
bax/callbacks.py
bax/data.py
bax/trainer.py
bax/utils.py
bax-0.1.12.dist-info/LICENSE
bax-0.1.12.dist-info/METADATA
bax-0.1.12.dist-info/WHEEL
bax-0.1.12.dist-info/top_level.txt
bax-0.1.12.dist-info/RECORD
