Metadata-Version: 2.1
Name: bax
Version: 0.1.12
Summary: A flexible trainer interface for Jax and Haiku.
Home-page: https://github.com/rystrauss/bax
Author: Ryan Strauss
Author-email: ryanrstrauss@icloud.com
License: LICENSE
Requires-Python: >=3.7
License-File: LICENSE
Requires-Dist: dm-haiku (>=0.0.6)
Requires-Dist: jax (>=0.3.13)
Requires-Dist: optax (>=0.1.2)
Requires-Dist: jmp (>=0.0.2)
Requires-Dist: chex (>=0.1.3)
Requires-Dist: keras (>=2.9.0)
Requires-Dist: tensorflow (>=2.9.0)
Requires-Dist: rich (>=12.4.1)
